MANIFEST.in
README.md
description.rst
setup.py
python_raven.egg-info/PKG-INFO
python_raven.egg-info/SOURCES.txt
python_raven.egg-info/dependency_links.txt
python_raven.egg-info/requires.txt
python_raven.egg-info/top_level.txt
raven/__init__.py
raven/demoserver.py
raven/flask_glue.py