Metadata-Version: 1.1
Name: python-raven
Version: 0.9.2.1
Summary: Compatability wrapper around python-ucam-webauth
Home-page: http://github.com/danielrichman/python-raven
Author: Daniel Richman
Author-email: main@danielrichman.co.uk
License: BSD-2-Clause
Keywords: Raven Cambridge ucam-webauth
Platform: UNKNOWN
Classifier: Intended Audience :: Developers
Classifier: License :: OSI Approved :: BSD License
Classifier: Operating System :: OS Independent
Classifier: Topic :: Internet :: WWW/HTTP :: Dynamic Content :: CGI Tools/Libraries
Classifier: Programming Language :: Python :: 2
Classifier: Programming Language :: Python :: 3
